maccabistats/__init__.py
maccabistats/maccabilogging.py
maccabistats/version.py
maccabistats/config/__init__.py
maccabistats/config/config.py
maccabistats/config/maccabipedia_config.py
maccabistats/config/maccabisite_config.py
maccabistats/data_improvement/__init__.py
maccabistats/data_improvement/naming_fixes.py
maccabistats/error_finder/__init__.py
maccabistats/error_finder/error_finder.py
maccabistats/github_actions_scripts/__init__.py
maccabistats/github_actions_scripts/fetch_games_from_maccabipedia.py
maccabistats/github_actions_scripts/find_maccabipedia_errors.py
maccabistats/github_actions_scripts/upload_maccabipedia_games_to_ftp.py
maccabistats/maccabipedia/__init__.py
maccabistats/maccabipedia/players.py
maccabistats/models/__init__.py
maccabistats/models/game_data.py
maccabistats/models/player.py
maccabistats/models/player_game_events.py
maccabistats/models/player_in_game.py
maccabistats/models/team.py
maccabistats/models/team_in_game.py
maccabistats/parse/__init__.py
maccabistats/parse/add_manual_games.py
maccabistats/parse/general_fixes.py
maccabistats/parse/maccabistats_source.py
maccabistats/parse/merge_sources.py
maccabistats/parse/name_normalization.py
maccabistats/parse/parse_from_all_sites.py
maccabistats/parse/sources.py
maccabistats/parse/teams_names_changer.py
maccabistats/parse/maccabi_tlv_site/__init__.py
maccabistats/parse/maccabi_tlv_site/fix_specific_games.py
maccabistats/parse/maccabi_tlv_site/game_events_parser.py
maccabistats/parse/maccabi_tlv_site/game_pages_provider.py
maccabistats/parse/maccabi_tlv_site/game_squads_parser.py
maccabistats/parse/maccabi_tlv_site/maccabi_tlv_site_source.py
maccabistats/parse/maccabi_tlv_site/main_parser.py
maccabistats/parse/maccabi_tlv_site/team_parser.py
maccabistats/parse/maccabipedia/__init__.py
maccabistats/parse/maccabipedia/maccabipedia_cargo_chunks_crawler.py
maccabistats/parse/maccabipedia/maccabipedia_parser.py
maccabistats/parse/maccabipedia/maccabipedia_single_file_source.py
maccabistats-2.51.dist-info/METADATA
maccabistats-2.51.dist-info/WHEEL
maccabistats-2.51.dist-info/top_level.txt
maccabistats-2.51.dist-info/RECORD
