Metadata-Version: 2.1
Name: maccabistats
Version: 2.51
Summary: Maccabi tel-aviv football team statistics manipulation.
Home-page: https://github.com/Maccabipedia/maccabistats
License: MIT
Project-URL: MaccabiPedia, https://www.maccabipedia.co.il
Requires-Python: >=3.11
Requires-Dist: requests<3,>=2.28
Requires-Dist: beautifulsoup4<5,>=4.12
Requires-Dist: lxml<5,>=4.9.1
Requires-Dist: python-dateutil<3,>=2.7
Requires-Dist: matplotlib<4,>=3.6.0
Requires-Dist: progressbar2<5,>=4.0.0
